swy/__init__.py
swy/__main__.py
swy/app.py
swy/config/__init__.py
swy/config/logging_config.py
swy/config/settings.py
swy/core/Manager.py
swy/core/__init__.py
swy/core/adb/AdbInterface.py
swy/core/adb/__init__.py
swy/core/exceptions/__init__.py
swy/core/exceptions/swyexceptions.py
swy/core/tools/__init__.py
swy/core/tools/init_tools.py
swy/data/__init__.py
swy/data/phones/SM_G950F.py
swy/data/phones/__init__.py
tests/__init__.py
swy-0.0.3.dist-info/LICENSE
swy-0.0.3.dist-info/METADATA
swy-0.0.3.dist-info/WHEEL
swy-0.0.3.dist-info/top_level.txt
swy-0.0.3.dist-info/RECORD
