Metadata-Version: 2.1
Name: swy
Version: 0.0.3
Summary: SWY Project
Home-page: https://github.com/Haytek/swy
Author: Haytek
Author-email: haytek34@gmail.com
License: UNKNOWN
Platform: UNKNOWN
Classifier: Programming Language :: Python :: 3.7
Classifier: Programming Language :: Python :: 3.8
Classifier: License :: OSI Approved :: GNU Lesser General Public License v3 (LGPLv3)
Classifier: Programming Language :: Python :: 3 :: Only
Classifier: Topic :: Games/Entertainment
Requires-Python: >=3.7
Requires-Dist: requests
